[
  {
    "dialog": "Greetings, Miss Wang. How do you fare this fine day? Please, do have a seat."
  },
  {
    "dialog": "Many thanks."
  },
  {
    "dialog": "In which subject did you specialize during your education, if I may inquire?"
  },
  {
    "dialog": "I studied Public Relations at the wizarding school of my choice."
  },
  {
    "dialog": "Have you put your education to use in the work world?"
  },
  {
    "dialog": "Indeed I have, sir. After graduation, I spent a year working in the export section of a trade company located in the wizarding city of Macao."
  },
  {
    "dialog": "What sorts of duties were you responsible for in that position?"
  },
  {
    "dialog": "My responsibilities included overseeing the successful export of various wizarding goods and products."
  },
  {
    "dialog": "Fascinating, you must have a good understanding of the complexities of export procedures."
  },
  {
    "dialog": "Indeed, I do, sir."
  },
  {
    "dialog": "Splendid. That will certainly come in useful."
  },
  {
    "dialog": "Where to, madam?"
  },
  {
    "dialog": "To the Grand Hotel, if you please."
  },
  {
    "dialog": "The Grand Hotel, you say?"
  },
  {
    "dialog": "Correct, do you know its location?"
  },
  {
    "dialog": "I'm afraid not, madam. I do not believe I am familiar with its location."
  },
  {
    "dialog": "It can be found on 11th Avenue, at the end of Park Street."
  },
  {
    "dialog": "Ah, yes! I know the location well now."
  },
  {
    "dialog": "Might I take your order now, madam?"
  },
  {
    "dialog": "Indeed, I'll start with a serving of the shrimp cocktail, if you please."
  }
]